my_jupyter_shared_docprovider/__init__.py
my_jupyter_shared_docprovider/labextension/package.json
my_jupyter_shared_docprovider/labextension/static/349.9f7b425f1756778e6e35.js
my_jupyter_shared_docprovider/labextension/static/523.f33f47222408f7bbe84b.js
my_jupyter_shared_docprovider/labextension/static/631.b30847c2ed2769e1f267.js
my_jupyter_shared_docprovider/labextension/static/730.9f7b425f1756778e6e35.js
my_jupyter_shared_docprovider/labextension/static/remoteEntry.f8cb77d3117840e486fc.js
my_jupyter_shared_docprovider/labextension/static/style.js
my_jupyter_shared_docprovider/labextension/static/third-party-licenses.json
my_jupyter_shared_docprovider-0.1.0.data/data/share/jupyter/labextensions/@jupyter/my-shared-docprovider-extension/package.json
my_jupyter_shared_docprovider-0.1.0.data/data/share/jupyter/labextensions/@jupyter/my-shared-docprovider-extension/static/349.9f7b425f1756778e6e35.js
my_jupyter_shared_docprovider-0.1.0.data/data/share/jupyter/labextensions/@jupyter/my-shared-docprovider-extension/static/523.f33f47222408f7bbe84b.js
my_jupyter_shared_docprovider-0.1.0.data/data/share/jupyter/labextensions/@jupyter/my-shared-docprovider-extension/static/631.b30847c2ed2769e1f267.js
my_jupyter_shared_docprovider-0.1.0.data/data/share/jupyter/labextensions/@jupyter/my-shared-docprovider-extension/static/730.9f7b425f1756778e6e35.js
my_jupyter_shared_docprovider-0.1.0.data/data/share/jupyter/labextensions/@jupyter/my-shared-docprovider-extension/static/remoteEntry.f8cb77d3117840e486fc.js
my_jupyter_shared_docprovider-0.1.0.data/data/share/jupyter/labextensions/@jupyter/my-shared-docprovider-extension/static/style.js
my_jupyter_shared_docprovider-0.1.0.data/data/share/jupyter/labextensions/@jupyter/my-shared-docprovider-extension/static/third-party-licenses.json
my_jupyter_shared_docprovider-0.1.0.data/data/share/jupyter/labextensions/@jupyter/my-shared-docprovider-extension/install.json
my_jupyter_shared_docprovider-0.1.0.dist-info/METADATA
my_jupyter_shared_docprovider-0.1.0.dist-info/WHEEL
my_jupyter_shared_docprovider-0.1.0.dist-info/licenses/LICENSE
my_jupyter_shared_docprovider-0.1.0.dist-info/RECORD
